ticterm/__init__.py
ticterm/esc/Style.py
ticterm/esc/__init__.py
ticterm/esc/color.py
ticterm/esc/style.py
ticterm/log/__init__.py
ticterm/log/styled_print.py
ticterm/log/styling.py
ticterm/log/Logger/Config.py
ticterm/log/Logger/Logger.py
ticterm/log/Logger/__init__.py
ticterm/log/Logger/lib.py
ticterm-0.2.1.post2.dist-info/METADATA
ticterm-0.2.1.post2.dist-info/WHEEL
ticterm-0.2.1.post2.dist-info/RECORD
