Metadata-Version: 2.4
Name: ticterm
Version: 0.2.1.post2
Project-URL: Repository, https://gitlab.com/tictaccc/python-ticterm
